primehub_job/__init__.py
primehub_job/from_jupyter.py
primehub_job/utils.py
primehub_job/view.py
primehub_job-0.1.3.dist-info/LICENSE
primehub_job-0.1.3.dist-info/METADATA
primehub_job-0.1.3.dist-info/WHEEL
primehub_job-0.1.3.dist-info/top_level.txt
primehub_job-0.1.3.dist-info/RECORD
