Metadata-Version: 2.1
Name: primehub-job
Version: 0.1.3
Summary: Submit PrimeHub jobs easier
Home-page: UNKNOWN
License: Apache License 2.0
Platform: UNKNOWN
Classifier: Development Status :: 2 - Pre-Alpha
Classifier: Programming Language :: Python :: 3
Classifier: Operating System :: OS Independent
Requires-Python: >=3
Requires-Dist: cloudpickle
Requires-Dist: requests
Requires-Dist: ipywidgets
